ptpm/__about__.py
ptpm/__init__.py
ptpm/get_todos.py
ptpm/main.py
ptpm/test/__init__.py
ptpm/test/test_get_todos.py
ptpm-1.0.2.dist-info/METADATA
ptpm-1.0.2.dist-info/WHEEL
ptpm-1.0.2.dist-info/entry_points.txt
ptpm-1.0.2.dist-info/licenses/LICENSE
ptpm-1.0.2.dist-info/RECORD
