Metadata-Version: 2.1
Name: ptpm
Version: 1.0.2
Summary: A simple project management tool that doesn't suck.
Project-URL: Issue Tracker, https://github.com/calvinloveland/plaintext_project_management
Project-URL: Repository, https://github.com/calvinloveland/plaintext_project_management
Author-email: Calvin Loveland <calvin@loveland.dev>
License-File: LICENSE
Classifier: License :: OSI Approved :: GNU General Public License v3 (GPLv3)
Classifier: Operating System :: OS Independent
Classifier: Programming Language :: Python :: 3.8
Requires-Python: >=3.8
Requires-Dist: gitpython
Requires-Dist: lazy-ci
Requires-Dist: loguru
Requires-Dist: pytest
Requires-Dist: tqdm
